{
  "source": "pcs",
  "schemaVersion": 1,
  "fetchedDate": "14 June 2025 23:25 GMT",
  "momentId": 191408,
  "team": {
    "owner": "Jonny Long",
    "name": "Ineos Grenadiers-Greenpeace-Poundland",
    "totalPoints": 5898.14,
    "riders": [
      {
        "name": "Jonas Vingegaard",
        "id": 112082,
        "team": "TVL",
        "country": "dk",
        "totalPoints": 438.57,
        "results": [
          {
            "name": "Critérium du Dauphiné - Stage 7",
            "date": "14 Jun 2025",
            "points": 40,
            "rank": 2
          },
          {
            "name": "Critérium du Dauphiné - Stage 6",
            "date": "13 Jun 2025",
            "points": 40,
            "rank": 2
          },
          {
            "name": "Critérium du Dauphiné - Stage 4 (ITT)",
            "date": "11 Jun 2025",
            "points": 40,
            "rank": 2
          },
          {
            "name": "Critérium du Dauphiné - Stage 1",
            "date": "8 Jun 2025",
            "points": 40,
            "rank": 2
          },
          {
            "name": "Paris-Nice - Stage 4",
            "date": "12 Mar 2025",
            "points": 40,
            "rank": 2
          },
          {
            "name": "Paris-Nice - Stage 4 - Bonus",
            "date": "12 Mar 2025",
            "points": 10
          },
          {
            "name": "Paris-Nice - Stage 3 (TTT)",
            "date": "11 Mar 2025",
            "points": 8.57,
            "rank": 1
          },
          {
            "name": "Volta ao Algarve em Bicicleta - General classification",
            "date": "23 Feb 2025",
            "points": 200,
            "rank": 1
          },
          {
            "name": "Volta ao Algarve em Bicicleta - Stage 5 (ITT)",
            "date": "23 Feb 2025",
            "points": 20,
            "rank": 1
          }
        ]
      },
      {
        "name": "Mattias Skjelmose",
        "id": 365033,
        "team": "LTK",
        "country": "dk",
        "totalPoints": 974.57,
        "results": [
          {
            "name": "Liège-Bastogne-Liège",
            "date": "27 Apr 2025",
            "points": 15,
            "rank": 39
          },
          {
            "name": "Amstel Gold Race",
            "date": "20 Apr 2025",
            "points": 500,
            "rank": 1
          },
          {
            "name": "Itzulia Basque Country - General classification",
            "date": "12 Apr 2025",
            "points": 180,
            "rank": 5
          },
          {
            "name": "Itzulia Basque Country - Stage 3",
            "date": "9 Apr 2025",
            "points": 10,
            "rank": 6
          },
          {
            "name": "Itzulia Basque Country - Stage 1 (ITT)",
            "date": "7 Apr 2025",
            "points": 6,
            "rank": 8
          },
          {
            "name": "Paris-Nice - Stage 6",
            "date": "14 Mar 2025",
            "points": 10,
            "rank": 7
          },
          {
            "name": "Paris-Nice - Stage 4",
            "date": "12 Mar 2025",
            "points": 30,
            "rank": 3
          },
          {
            "name": "Paris-Nice - Stage 3 (TTT)",
            "date": "11 Mar 2025",
            "points": 3.57,
            "rank": 4
          },
          {
            "name": "Faun Drome Classic",
            "date": "2 Mar 2025",
            "points": 150,
            "rank": 2
          },
          {
            "name": "Faun-Ardèche Classic",
            "date": "1 Mar 2025",
            "points": 70,
            "rank": 6
          }
        ]
      },
      {
        "name": "Enric Mas",
        "id": 109803,
        "team": "MOV",
        "country": "es",
        "totalPoints": 721,
        "results": [
          {
            "name": "Critérium du Dauphiné - Stage 7",
            "date": "14 Jun 2025",
            "points": 10,
            "rank": 7
          },
          {
            "name": "Itzulia Basque Country - General classification",
            "date": "12 Apr 2025",
            "points": 320,
            "rank": 2
          },
          {
            "name": "Itzulia Basque Country - Stage 6",
            "date": "12 Apr 2025",
            "points": 30,
            "rank": 2
          },
          {
            "name": "Itzulia Basque Country - Stage 3",
            "date": "9 Apr 2025",
            "points": 15,
            "rank": 5
          },
          {
            "name": "Volta Ciclista a Catalunya - General classification",
            "date": "30 Mar 2025",
            "points": 260,
            "rank": 3
          },
          {
            "name": "Volta Ciclista a Catalunya - Stage 4",
            "date": "27 Mar 2025",
            "points": 25,
            "rank": 3
          },
          {
            "name": "Volta Ciclista a Catalunya - Stage 3",
            "date": "26 Mar 2025",
            "points": 10,
            "rank": 6
          },
          {
            "name": "Faun Drome Classic",
            "date": "2 Mar 2025",
            "points": 3,
            "rank": 32
          },
          {
            "name": "Faun-Ardèche Classic",
            "date": "1 Mar 2025",
            "points": 40,
            "rank": 9
          },
          {
            "name": "Vuelta a Andalucia Ruta Ciclista Del Sol - General classification",
            "date": "23 Feb 2025",
            "points": 5,
            "rank": 18
          },
          {
            "name": "Vuelta a Andalucia Ruta Ciclista Del Sol - Stage 2",
            "date": "20 Feb 2025",
            "points": 3,
            "rank": 5
          }
        ]
      },
      {
        "name": "Oscar Onley",
        "id": 1710249,
        "team": "TPP",
        "country": "gb",
        "totalPoints": 782,
        "results": [
          {
            "name": "Tour de Romandie - General classification",
            "date": "4 May 2025",
            "points": 30,
            "rank": 16
          },
          {
            "name": "Tour de Romandie - Stage 3",
            "date": "2 May 2025",
            "points": 5,
            "rank": 9
          },
          {
            "name": "Tour de Romandie - Stage 1",
            "date": "30 Apr 2025",
            "points": 15,
            "rank": 6
          },
          {
            "name": "Liège-Bastogne-Liège",
            "date": "27 Apr 2025",
            "points": 95,
            "rank": 12
          },
          {
            "name": "Itzulia Basque Country - General classification",
            "date": "12 Apr 2025",
            "points": 80,
            "rank": 9
          },
          {
            "name": "Itzulia Basque Country - Stage 6",
            "date": "12 Apr 2025",
            "points": 6,
            "rank": 8
          },
          {
            "name": "Itzulia Basque Country - Stage 4",
            "date": "10 Apr 2025",
            "points": 6,
            "rank": 8
          },
          {
            "name": "Gran Premio Miguel Indurain",
            "date": "5 Apr 2025",
            "points": 5,
            "rank": 16
          },
          {
            "name": "UAE Tour - General classification",
            "date": "23 Feb 2025",
            "points": 120,
            "rank": 5
          },
          {
            "name": "UAE Tour - Stage 7",
            "date": "23 Feb 2025",
            "points": 10,
            "rank": 5
          },
          {
            "name": "UAE Tour - Stage 3",
            "date": "19 Feb 2025",
            "points": 25,
            "rank": 2
          },
          {
            "name": "UAE Tour - Stage 1",
            "date": "17 Feb 2025",
            "points": 10,
            "rank": 5
          },
          {
            "name": "Cadel Evans Great Ocean Road Race - Men",
            "date": "2 Feb 2025",
            "points": 60,
            "rank": 9
          },
          {
            "name": "Santos Tour Down Under - General classification",
            "date": "26 Jan 2025",
            "points": 275,
            "rank": 4
          },
          {
            "name": "Santos Tour Down Under - Stage 5",
            "date": "25 Jan 2025",
            "points": 40,
            "rank": 2
          }
        ]
      },
      {
        "name": "Santiago Buitrago",
        "id": 353375,
        "team": "TBV",
        "country": "co",
        "totalPoints": 675,
        "results": [
          {
            "name": "Liège-Bastogne-Liège",
            "date": "27 Apr 2025",
            "points": 15,
            "rank": 37
          },
          {
            "name": "La Flèche Wallonne",
            "date": "23 Apr 2025",
            "points": 140,
            "rank": 6
          },
          {
            "name": "Amstel Gold Race",
            "date": "20 Apr 2025",
            "points": 20,
            "rank": 29
          },
          {
            "name": "Itzulia Basque Country - General classification",
            "date": "12 Apr 2025",
            "points": 40,
            "rank": 13
          },
          {
            "name": "Tour des Alpes-Maritimes - General classification",
            "date": "23 Feb 2025",
            "points": 85,
            "rank": 2
          },
          {
            "name": "Tour des Alpes-Maritimes - Stage 1",
            "date": "22 Feb 2025",
            "points": 5,
            "rank": 2
          },
          {
            "name": "Classic Var",
            "date": "21 Feb 2025",
            "points": 50,
            "rank": 5
          },
          {
            "name": "Volta a la Comunitat Valenciana - General classification",
            "date": "9 Feb 2025",
            "points": 200,
            "rank": 1
          },
          {
            "name": "Volta a la Comunitat Valenciana - Stage 4",
            "date": "8 Feb 2025",
            "points": 20,
            "rank": 1
          },
          {
            "name": "Volta a la Comunitat Valenciana - Stage 4 - Bonus",
            "date": "8 Feb 2025",
            "points": 5
          },
          {
            "name": "Volta a la Comunitat Valenciana - Stage 3",
            "date": "7 Feb 2025",
            "points": 15,
            "rank": 2
          },
          {
            "name": "Volta a la Comunitat Valenciana - Stage 2",
            "date": "6 Feb 2025",
            "points": 20,
            "rank": 1
          },
          {
            "name": "Clàssica Comunitat Valenciana 1969 - Gran Premi València",
            "date": "26 Jan 2025",
            "points": 60,
            "rank": 4
          }
        ]
      },
      {
        "name": "Christophe Laporte",
        "id": 81980,
        "team": "TVL",
        "country": "fr",
        "totalPoints": 0,
        "results": []
      },
      {
        "name": "Valentin Madouas",
        "id": 91637,
        "team": "GFC",
        "country": "fr",
        "totalPoints": 296,
        "results": [
          {
            "name": "Tro-Bro Léon",
            "date": "11 May 2025",
            "points": 125,
            "rank": 3
          },
          {
            "name": "Boucles de l'Aulne - Châteaulin",
            "date": "8 May 2025",
            "points": 3,
            "rank": 23
          },
          {
            "name": "La Flèche Wallonne",
            "date": "23 Apr 2025",
            "points": 16,
            "rank": 26
          },
          {
            "name": "Amstel Gold Race",
            "date": "20 Apr 2025",
            "points": 30,
            "rank": 19
          },
          {
            "name": "Ronde van Vlaanderen - Tour des Flandres ME",
            "date": "6 Apr 2025",
            "points": 50,
            "rank": 17
          },
          {
            "name": "Gent-Wevelgem in Flanders Fields ME",
            "date": "30 Mar 2025",
            "points": 10,
            "rank": 32
          },
          {
            "name": "E3 Saxo Classic ME",
            "date": "28 Mar 2025",
            "points": 24,
            "rank": 17
          },
          {
            "name": "Tirreno-Adriatico - General classification",
            "date": "16 Mar 2025",
            "points": 10,
            "rank": 35
          },
          {
            "name": "Strade Bianche",
            "date": "8 Mar 2025",
            "points": 8,
            "rank": 39
          },
          {
            "name": "Faun Drome Classic",
            "date": "2 Mar 2025",
            "points": 15,
            "rank": 14
          },
          {
            "name": "Faun-Ardèche Classic",
            "date": "1 Mar 2025",
            "points": 5,
            "rank": 29
          }
        ]
      },
      {
        "name": "Geraint Thomas",
        "id": 32532,
        "team": "IGD",
        "country": "gb",
        "totalPoints": 28,
        "results": [
          {
            "name": "Tour de Romandie - General classification",
            "date": "4 May 2025",
            "points": 20,
            "rank": 28
          },
          {
            "name": "Volta Ciclista a Catalunya - General classification",
            "date": "30 Mar 2025",
            "points": 8,
            "rank": 45
          }
        ]
      },
      {
        "name": "Christian Scaroni",
        "id": 144019,
        "team": "XAT",
        "country": "it",
        "totalPoints": 1306,
        "results": [
          {
            "name": "Giro d'Italia - Mountains classification",
            "date": "1 Jun 2025",
            "points": 130,
            "rank": 2
          },
          {
            "name": "Giro d'Italia - General classification",
            "date": "1 Jun 2025",
            "points": 25,
            "rank": 40
          },
          {
            "name": "Giro d'Italia - Stage 18",
            "date": "29 May 2025",
            "points": 5,
            "rank": 14
          },
          {
            "name": "Giro d'Italia - Stage 16",
            "date": "27 May 2025",
            "points": 180,
            "rank": 1
          },
          {
            "name": "Giro d'Italia - Stage 15",
            "date": "25 May 2025",
            "points": 95,
            "rank": 3
          },
          {
            "name": "Giro d'Italia - Stage 3",
            "date": "11 May 2025",
            "points": 30,
            "rank": 9
          },
          {
            "name": "Liège-Bastogne-Liège",
            "date": "27 Apr 2025",
            "points": 30,
            "rank": 23
          },
          {
            "name": "La Flèche Wallonne",
            "date": "23 Apr 2025",
            "points": 16,
            "rank": 23
          },
          {
            "name": "Trofeo Laigueglia",
            "date": "5 Mar 2025",
            "points": 150,
            "rank": 2
          },
          {
            "name": "Faun-Ardèche Classic",
            "date": "1 Mar 2025",
            "points": 85,
            "rank": 5
          },
          {
            "name": "Tour des Alpes-Maritimes - General classification",
            "date": "23 Feb 2025",
            "points": 125,
            "rank": 1
          },
          {
            "name": "Tour des Alpes-Maritimes - Stage 1",
            "date": "22 Feb 2025",
            "points": 14,
            "rank": 1
          },
          {
            "name": "Tour des Alpes-Maritimes - Stage 1 - Bonus",
            "date": "22 Feb 2025",
            "points": 3
          },
          {
            "name": "Classic Var",
            "date": "21 Feb 2025",
            "points": 125,
            "rank": 1
          },
          {
            "name": "Vuelta a la Región de Murcia ''Costa Cálida''",
            "date": "15 Feb 2025",
            "points": 70,
            "rank": 3
          },
          {
            "name": "Trofeo Serra Tramuntana",
            "date": "31 Jan 2025",
            "points": 3,
            "rank": 17
          },
          {
            "name": "Trofeo Calvià",
            "date": "29 Jan 2025",
            "points": 85,
            "rank": 2
          },
          {
            "name": "Clàssica Comunitat Valenciana 1969 - Gran Premi València",
            "date": "26 Jan 2025",
            "points": 85,
            "rank": 2
          },
          {
            "name": "Gran Premio Castellón - Ruta de la Cerámica",
            "date": "25 Jan 2025",
            "points": 50,
            "rank": 5
          }
        ]
      },
      {
        "name": "Antonio Tiberi",
        "id": 308040,
        "team": "TBV",
        "country": "it",
        "totalPoints": 677,
        "results": [
          {
            "name": "Giro d'Italia - General classification",
            "date": "1 Jun 2025",
            "points": 70,
            "rank": 17
          },
          {
            "name": "Giro d'Italia - Stage 19",
            "date": "30 May 2025",
            "points": 30,
            "rank": 9
          },
          {
            "name": "Giro d'Italia - Stage 16",
            "date": "27 May 2025",
            "points": 2,
            "rank": 15
          },
          {
            "name": "Giro d'Italia - Stage 13",
            "date": "23 May 2025",
            "points": 40,
            "rank": 7
          },
          {
            "name": "Giro d'Italia - Stage 11",
            "date": "21 May 2025",
            "points": 45,
            "rank": 6
          },
          {
            "name": "Giro d'Italia - Stage 9",
            "date": "18 May 2025",
            "points": 45,
            "rank": 6
          },
          {
            "name": "Giro d'Italia - Stage 7",
            "date": "16 May 2025",
            "points": 45,
            "rank": 6
          },
          {
            "name": "Giro d'Italia - Stage 1",
            "date": "9 May 2025",
            "points": 15,
            "rank": 12
          },
          {
            "name": "Tirreno-Adriatico - General classification",
            "date": "16 Mar 2025",
            "points": 325,
            "rank": 3
          },
          {
            "name": "Tirreno-Adriatico - Stage 6",
            "date": "15 Mar 2025",
            "points": 20,
            "rank": 5
          },
          {
            "name": "Tirreno-Adriatico - Stage 1 (ITT)",
            "date": "10 Mar 2025",
            "points": 25,
            "rank": 4
          },
          {
            "name": "Volta ao Algarve em Bicicleta - General classification",
            "date": "23 Feb 2025",
            "points": 5,
            "rank": 16
          },
          {
            "name": "Volta ao Algarve em Bicicleta - Stage 5 (ITT)",
            "date": "23 Feb 2025",
            "points": 10,
            "rank": 3
          }
        ]
      }
    ]
  }
}
